kxy_open_id_client/__init__.py
kxy_open_id_client/client.py
kxy_open_id_client/exceptions.py
kxy_open_id_client/models.py
kxy_open_id_client-0.2.1.dist-info/licenses/LICENSE
kxy_open_id_client-0.2.1.dist-info/METADATA
kxy_open_id_client-0.2.1.dist-info/WHEEL
kxy_open_id_client-0.2.1.dist-info/top_level.txt
kxy_open_id_client-0.2.1.dist-info/RECORD
