Metadata-Version: 2.4
Name: kxy-open-id-client
Version: 0.2.1
Summary: Client library for KXY Open ID Service - ID segment allocation
Author: KXY Development Team
License: MIT
Project-URL: Homepage, https://github.com/kxy/kxy-open-id-client
Project-URL: Documentation, https://github.com/kxy/kxy-open-id-client#readme
Project-URL: Repository, https://github.com/kxy/kxy-open-id-client
Project-URL: Issues, https://github.com/kxy/kxy-open-id-client/issues
Keywords: kxy,open-id,id-generator,distributed-id,segment
Classifier: Development Status :: 4 - Beta
Classifier: Intended Audience :: Developers
Classifier: License :: OSI Approved :: MIT License
Classifier: Programming Language :: Python :: 3
Classifier: Programming Language :: Python :: 3.8
Classifier: Programming Language :: Python :: 3.9
Classifier: Programming Language :: Python :: 3.10
Classifier: Programming Language :: Python :: 3.11
Classifier: Programming Language :: Python :: 3.12
Classifier: Topic :: Software Development :: Libraries :: Python Modules
Requires-Python: >=3.8
License-File: LICENSE
Requires-Dist: httpx>=0.24.0
Requires-Dist: pydantic>=2.0.0
Provides-Extra: dev
Requires-Dist: pytest>=7.0.0; extra == "dev"
Requires-Dist: pytest-asyncio>=0.21.0; extra == "dev"
Requires-Dist: pytest-cov>=4.0.0; extra == "dev"
Requires-Dist: black>=23.0.0; extra == "dev"
Requires-Dist: flake8>=6.0.0; extra == "dev"
Requires-Dist: mypy>=1.0.0; extra == "dev"
Dynamic: license-file
